playbooks/__init__.py
playbooks/__main__.py
playbooks/agent_clients/__init__.py
playbooks/agents/__init__.py
playbooks/agents/agent_builder.py
playbooks/agents/ai_agent.py
playbooks/agents/async_queue.py
playbooks/agents/base_agent.py
playbooks/agents/builtin_playbooks.py
playbooks/agents/delivery_preferences.py
playbooks/agents/human_agent.py
playbooks/agents/local_ai_agent.py
playbooks/agents/mcp_agent.py
playbooks/agents/messaging_mixin.py
playbooks/agents/namespace_manager.py
playbooks/agents/registry.py
playbooks/agents/remote_ai_agent.py
playbooks/applications/__init__.py
playbooks/applications/agent_chat.py
playbooks/applications/cli_utility.py
playbooks/applications/human_wait.py
playbooks/applications/playbooks_playground.html
playbooks/applications/streaming_observer.py
playbooks/applications/web_server.py
playbooks/channels/__init__.py
playbooks/channels/channel.py
playbooks/channels/participant.py
playbooks/channels/stream_events.py
playbooks/cli.py
playbooks/compilation/__init__.py
playbooks/compilation/compiler.py
playbooks/compilation/expression_engine.py
playbooks/compilation/import_processor.py
playbooks/compilation/loader.py
playbooks/compilation/markdown_to_ast.py
playbooks/compilation/parse_utils.py
playbooks/config.py
playbooks/core/__init__.py
playbooks/core/argument_types.py
playbooks/core/constants.py
playbooks/core/enums.py
playbooks/core/events.py
playbooks/core/exceptions.py
playbooks/core/identifiers.py
playbooks/core/message.py
playbooks/core/stream_result.py
playbooks/debug/__init__.py
playbooks/debug/debug_handler.py
playbooks/debug/server.py
playbooks/execution/__init__.py
playbooks/execution/agents_accessor.py
playbooks/execution/base.py
playbooks/execution/call.py
playbooks/execution/incremental_code_buffer.py
playbooks/execution/interpreter_prompt.py
playbooks/execution/llm_response.py
playbooks/execution/playbook.py
playbooks/execution/python_executor.py
playbooks/execution/raw.py
playbooks/execution/react.py
playbooks-0.7.3.dist-info/METADATA
playbooks-0.7.3.dist-info/WHEEL
playbooks-0.7.3.dist-info/entry_points.txt
playbooks-0.7.3.dist-info/licenses/LICENSE
playbooks-0.7.3.dist-info/RECORD
