Metadata-Version: 2.4
Name: playbooks
Version: 0.7.3
Summary: A framework for creating AI applications and agents using natural language programming
License: MIT
License-File: LICENSE
Author: Amol Kelkar
Author-email: kelkar.amol@gmail.com
Requires-Python: >=3.12,<4.0
Classifier: License :: OSI Approved :: MIT License
Classifier: Programming Language :: Python :: 3
Classifier: Programming Language :: Python :: 3.12
Classifier: Programming Language :: Python :: 3.13
Classifier: Programming Language :: Python :: 3.14
Requires-Dist: apscheduler (>=3.11.1,<4.0.0)
Requires-Dist: bidict (>=0.23.1,<0.24.0)
Requires-Dist: diskcache (>=5.6.3,<6.0.0)
Requires-Dist: dotenv (>=0.9.9,<0.10.0)
Requires-Dist: fastapi (>=0.122.0,<0.123.0)
Requires-Dist: fastapi-sso (>=0.18.0,<0.19.0)
Requires-Dist: fastmcp (>=2.13.1,<3.0.0)
Requires-Dist: langfuse (>=3.10.1,<4.0.0)
Requires-Dist: litellm (>=1.80.5,<2.0.0)
Requires-Dist: markdown-it-py (>=4.0.0,<5.0.0)
Requires-Dist: orjson (>=3.11.4,<4.0.0)
Requires-Dist: platformdirs (>=4.5.0,<5.0.0)
Requires-Dist: pydantic (>=2.12.4,<3.0.0)
Requires-Dist: python-box (>=7.3.2,<8.0.0)
Requires-Dist: python-frontmatter (>=1.1.0,<2.0.0)
Requires-Dist: redis (>=7.1.0,<8.0.0)
Requires-Dist: rich (>=14.2.0,<15.0.0)
Requires-Dist: simpleeval (>=1.0.3,<2.0.0)
Requires-Dist: websockets (>=15.0.1,<16.0.0)
